heave/__init__.py
heave/__main__.py
heave/cli.py
heave/file.py
heave/sql.py
heave-0.4.0.dist-info/METADATA
heave-0.4.0.dist-info/WHEEL
heave-0.4.0.dist-info/entry_points.txt
heave-0.4.0.dist-info/RECORD
