Metadata-Version: 2.3
Name: heave
Version: 0.4.0
Summary: CLI tool to batch update or insert data.
Author-email: Jonathan Biemond <jonathan.biemond@devrygreenhouses.com>
License-Expression: MIT
Requires-Python: >=3.10
Requires-Dist: click>=8.1.7
Requires-Dist: psycopg[binary]>=3.2.1
Requires-Dist: sqlalchemy>=2.0.32
